llm_pdf_to_images.py
llm_pdf_to_images-0.1.dist-info/licenses/LICENSE
llm_pdf_to_images-0.1.dist-info/METADATA
llm_pdf_to_images-0.1.dist-info/WHEEL
llm_pdf_to_images-0.1.dist-info/entry_points.txt
llm_pdf_to_images-0.1.dist-info/top_level.txt
llm_pdf_to_images-0.1.dist-info/RECORD
