Metadata-Version: 2.4
Name: llm-pdf-to-images
Version: 0.1
Summary: LLM fragment plugin to load a PDF as a sequence of images
Author: Simon Willison
License-Expression: Apache-2.0
Project-URL: Homepage, https://github.com/simonw/llm-pdf-to-images
Project-URL: Changelog, https://github.com/simonw/llm-pdf-to-images/releases
Project-URL: Issues, https://github.com/simonw/llm-pdf-to-images/issues
Project-URL: CI, https://github.com/simonw/llm-pdf-to-images/actions
Requires-Python: >=3.9
License-File: LICENSE
Requires-Dist: llm
Requires-Dist: PyMuPDF
Provides-Extra: test
Requires-Dist: pytest; extra == "test"
Dynamic: license-file
